{
  "campaign": "2026-06-02-hook-consolidation",
  "status": "draft",
  "branch_strategy": "stacked",
  "created_at": "2026-06-02T00:00:00+00:00",
  "sub_iterates": [
    {
      "id": "B0",
      "slug": "phase-resolver-contract",
      "spec_path": ".shipwright/planning/iterate/campaigns/2026-06-02-hook-consolidation/sub-iterates/B0-phase-resolver-contract.md",
      "status": "pending",
      "commit": null,
      "branch": null,
      "tests_passed": null,
      "tests_total": null
    },
    {
      "id": "B1",
      "slug": "stop-dispatcher",
      "spec_path": ".shipwright/planning/iterate/campaigns/2026-06-02-hook-consolidation/sub-iterates/B1-stop-dispatcher.md",
      "status": "pending",
      "commit": null,
      "branch": null,
      "tests_passed": null,
      "tests_total": null
    },
    {
      "id": "B2",
      "slug": "sessionstart-dispatcher",
      "spec_path": ".shipwright/planning/iterate/campaigns/2026-06-02-hook-consolidation/sub-iterates/B2-sessionstart-dispatcher.md",
      "status": "pending",
      "commit": null,
      "branch": null,
      "tests_passed": null,
      "tests_total": null
    },
    {
      "id": "B3",
      "slug": "userpromptsubmit-dispatcher",
      "spec_path": ".shipwright/planning/iterate/campaigns/2026-06-02-hook-consolidation/sub-iterates/B3-userpromptsubmit-dispatcher.md",
      "status": "pending",
      "commit": null,
      "branch": null,
      "tests_passed": null,
      "tests_total": null
    },
    {
      "id": "B4",
      "slug": "posttooluse-dispatcher",
      "spec_path": ".shipwright/planning/iterate/campaigns/2026-06-02-hook-consolidation/sub-iterates/B4-posttooluse-dispatcher.md",
      "status": "pending",
      "commit": null,
      "branch": null,
      "tests_passed": null,
      "tests_total": null
    },
    {
      "id": "B5",
      "slug": "pretooluse-crossphase",
      "spec_path": ".shipwright/planning/iterate/campaigns/2026-06-02-hook-consolidation/sub-iterates/B5-pretooluse-crossphase.md",
      "status": "pending",
      "commit": null,
      "branch": null,
      "tests_passed": null,
      "tests_total": null
    },
    {
      "id": "B6",
      "slug": "docs-and-tests",
      "spec_path": ".shipwright/planning/iterate/campaigns/2026-06-02-hook-consolidation/sub-iterates/B6-docs-and-tests.md",
      "status": "pending",
      "commit": null,
      "branch": null,
      "tests_passed": null,
      "tests_total": null
    }
  ]
}